._nanolab
nanolab/.___init__.py
nanolab/._command
nanolab/._decorators.py
nanolab/._loggers
nanolab/._main.py
nanolab/._node_interaction.py
nanolab/._publisher
nanolab/._pycmd.py
nanolab/._snippets
nanolab/._src
nanolab/._xnomin
nanolab/__init__.py
nanolab/decorators.py
nanolab/main.py
nanolab/node_interaction.py
nanolab/pycmd.py
nanolab/command/.___init__.py
nanolab/command/._command.py
nanolab/command/._mixins
nanolab/command/__init__.py
nanolab/command/command.py
nanolab/command/mixins/.___init__.py
nanolab/command/mixins/._base_mixin.py
nanolab/command/mixins/._bash_command_mixin.py
nanolab/command/mixins/._python_command_mixin.py
nanolab/command/mixins/._threaded_command_mixin.py
nanolab/command/mixins/__init__.py
nanolab/command/mixins/base_mixin.py
nanolab/command/mixins/bash_command_mixin.py
nanolab/command/mixins/python_command_mixin.py
nanolab/command/mixins/threaded_command_mixin.py
nanolab/loggers/.___init__.py
nanolab/loggers/._builders.py
nanolab/loggers/._contracts.py
nanolab/loggers/._factories
nanolab/loggers/._logger_manager.py
nanolab/loggers/._sinks
nanolab/loggers/._sources
nanolab/loggers/__init__.py
nanolab/loggers/builders.py
nanolab/loggers/contracts.py
nanolab/loggers/logger_manager.py
nanolab/loggers/factories/.___init__.py
nanolab/loggers/factories/._logger_factory.py
nanolab/loggers/factories/._sink_factory.py
nanolab/loggers/factories/__init__.py
nanolab/loggers/factories/logger_factory.py
nanolab/loggers/factories/sink_factory.py
nanolab/loggers/sinks/.___init__.py
nanolab/loggers/sinks/._console_sink.py
nanolab/loggers/sinks/._csv_sink.py
nanolab/loggers/sinks/._sql_sink.py
nanolab/loggers/sinks/__init__.py
nanolab/loggers/sinks/console_sink.py
nanolab/loggers/sinks/csv_sink.py
nanolab/loggers/sinks/sql_sink.py
nanolab/loggers/sources/.___init__.py
nanolab/loggers/sources/._rpc_logger.py
nanolab/loggers/sources/__init__.py
nanolab/loggers/sources/rpc_logger.py
nanolab/publisher/.___init__.py
nanolab/publisher/._block_asserts.py
nanolab-0.0.27.dist-info/METADATA
nanolab-0.0.27.dist-info/WHEEL
nanolab-0.0.27.dist-info/entry_points.txt
nanolab-0.0.27.dist-info/top_level.txt
nanolab-0.0.27.dist-info/RECORD
