Metadata-Version: 2.1
Name: nanolab
Version: 0.0.27
Summary: testing tool using nanomock
Home-page: https://github.com/gr0vity-dev/nanolab
Author: gr0vity
License: UNKNOWN
Platform: UNKNOWN
Requires-Dist: aiohttp
Requires-Dist: nanolog-parser
Requires-Dist: nanomock (>=0.0.14)
Requires-Dist: py-ed25519-blake2b
Requires-Dist: requests
Requires-Dist: sqlalchemy
